morningpy/__init__.py
morningpy/_version.py
morningpy/api/__init__.py
morningpy/api/market.py
morningpy/api/news.py
morningpy/api/security.py
morningpy/api/ticker.py
morningpy/api/timeseries.py
morningpy/config/__init__.py
morningpy/config/market.py
morningpy/config/news.py
morningpy/config/security.py
morningpy/config/ticker.py
morningpy/config/timeseries.py
morningpy/core/__init__.py
morningpy/core/auth.py
morningpy/core/base_extract.py
morningpy/core/cache.py
morningpy/core/client.py
morningpy/core/config.py
morningpy/core/dataframe_schema.py
morningpy/core/decorator.py
morningpy/core/error.py
morningpy/core/interchange.py
morningpy/core/security_loader.py
morningpy/data/cache.json
morningpy/data/tickers.parquet
morningpy/extractor/__init__.py
morningpy/extractor/market.py
morningpy/extractor/news.py
morningpy/extractor/security.py
morningpy/extractor/ticker.py
morningpy/extractor/timeseries.py
morningpy/schema/__init__.py
morningpy/schema/market.py
morningpy/schema/news.py
morningpy/schema/security.py
morningpy/schema/ticker.py
morningpy/schema/timeseries.py
morningpy-0.1.5.dist-info/LICENSE
morningpy-0.1.5.dist-info/METADATA
morningpy-0.1.5.dist-info/WHEEL
morningpy-0.1.5.dist-info/top_level.txt
morningpy-0.1.5.dist-info/RECORD
