Metadata-Version: 2.1
Name: morningpy
Version: 0.1.5
Summary: A Python wrapper to fetch financial data from Morningstar
Author-email: Thomas Piton <ton.email@example.com>
License: MIT License
Project-URL: homepage, https://github.com/ThomasPiton/morningpy
Project-URL: documentation, https://github.com/ThomasPiton/morningpy
Project-URL: repository, https://github.com/ThomasPiton/morningpy
Keywords: finance,morningstar,investing,stocks,ETF
Classifier: Programming Language :: Python :: 3
Classifier: Programming Language :: Python :: 3 :: Only
Classifier: Programming Language :: Python :: 3.11
Classifier: Programming Language :: Python :: 3.12
Classifier: Programming Language :: Python :: 3.13
Classifier: License :: OSI Approved :: MIT License
Classifier: Operating System :: OS Independent
Requires-Python: >=3.11
License-File: LICENSE
Requires-Dist: aiohttp>=3.13
Requires-Dist: dask>=2023.0
Requires-Dist: modin>=0.37
Requires-Dist: pandas>=2.3
Requires-Dist: polars>=1.35
Requires-Dist: pyarrow>=12
Requires-Dist: requests>=2.32
Requires-Dist: selenium>=4.38
Provides-Extra: dev
Requires-Dist: pytest>=7.0; extra == "dev"
Requires-Dist: black>=23.0; extra == "dev"
Requires-Dist: mypy>=1.0; extra == "dev"
